device_config/__init__.py
device_config/netconf_to_xml.py
DIAL_API_THULASI2024-1.0.0.dist-info/LICENSE
DIAL_API_THULASI2024-1.0.0.dist-info/METADATA
DIAL_API_THULASI2024-1.0.0.dist-info/WHEEL
DIAL_API_THULASI2024-1.0.0.dist-info/top_level.txt
DIAL_API_THULASI2024-1.0.0.dist-info/RECORD
