Metadata-Version: 2.1
Name: DIAL-API-THULASI2024
Version: 1.0.0
Summary: Dail_API
Home-page: UNKNOWN
Author: Kadiyala Thulasi Ram
Author-email: thulasiramchowdary1999@gmail.com
License: UNKNOWN
Platform: UNKNOWN
License-File: LICENSE
Requires-Dist: argparse
Requires-Dist: langchain
Requires-Dist: langchain-google-genai
Requires-Dist: ncclient
Requires-Dist: xmltodict
